app_server/__init__.py
app_server/app_wrapper.py
app_server/dispatcher.py
app_server/proxy.py
app_server/request_handler.py
app_server/shared_data.py
app_server/utils.py
app_server-1.0.2.dist-info/licenses/LICENSE
app_server-1.0.2.dist-info/METADATA
app_server-1.0.2.dist-info/WHEEL
app_server-1.0.2.dist-info/entry_points.txt
app_server-1.0.2.dist-info/top_level.txt
app_server-1.0.2.dist-info/RECORD
