Metadata-Version: 2.4
Name: app_server
Version: 1.0.2
Summary: a lightweight web application launcher for gunicorn and static files.
Home-page: https://github.com/viur-framework/viur-app_server
Author: Arne Gudermann
Author-email: ag@mausbrand.de
Project-URL: Bug Tracker, https://github.com/viur-framework/viur-app_server/issues
Classifier: Programming Language :: Python :: 3
Classifier: Operating System :: OS Independent
Requires-Python: >=3.8
License-File: LICENSE
Requires-Dist: werkzeug~=3.1.2
Requires-Dist: pyyaml~=6.0
Requires-Dist: gunicorn~=23.0.0
Requires-Dist: fs~=2.4.16
Requires-Dist: grpcio>=1.58.0
Dynamic: license-file
